<?xml version="1.0" encoding="utf-8" ?>
<dwsync>
<file name="doom.png" server="rjcoughlin.aisites.com" local="130711034280000000" remote="130716094800000000" Dst="2" />
<file name="handsUpFurg.png" server="rjcoughlin.aisites.com" local="130711034340000000" remote="130716094800000000" Dst="2" />
<file name="fuzz.png" server="rjcoughlin.aisites.com" local="130711034360000000" remote="130716094800000000" Dst="2" />
<file name="horn.png" server="rjcoughlin.aisites.com" local="130711034300000000" remote="130716094800000000" Dst="2" />
<file name="shroom.png" server="rjcoughlin.aisites.com" local="130711034400000000" remote="130716094800000000" Dst="2" />
<file name="paperBags.png" server="rjcoughlin.aisites.com" local="130711034380000000" remote="130716094800000000" Dst="2" />
<file name="smoke.png" server="rjcoughlin.aisites.com" local="130711034400000000" remote="130716094800000000" Dst="2" />
<file name="wolf.png" server="rjcoughlin.aisites.com" local="130711034460000000" remote="130716094800000000" Dst="2" />
<file name="handsUpFurg.png" server="ryan-coughlin.com//public_html/" local="130711034340000000" remote="130723399800000000" Dst="2" />
<file name="fuzz.png" server="ryan-coughlin.com//public_html/" local="130711034360000000" remote="130723399800000000" Dst="2" />
<file name="horn.png" server="ryan-coughlin.com//public_html/" local="130711034300000000" remote="130723399800000000" Dst="2" />
<file name="doom.png" server="ryan-coughlin.com//public_html/" local="130711034280000000" remote="130723399800000000" Dst="2" />
<file name="shroom.png" server="ryan-coughlin.com//public_html/" local="130711034400000000" remote="130723399800000000" Dst="2" />
<file name="smoke.png" server="ryan-coughlin.com//public_html/" local="130711034400000000" remote="130723399800000000" Dst="2" />
<file name="paperBags.png" server="ryan-coughlin.com//public_html/" local="130711034380000000" remote="130723399800000000" Dst="2" />
<file name="wolf.png" server="ryan-coughlin.com//public_html/" local="130711034460000000" remote="130723399800000000" Dst="2" />
</dwsync>